MsCoppelPVM/Base.py
MsCoppelPVM/ErrorMs.py
MsCoppelPVM/Fork.py
MsCoppelPVM/ForkHttp.py
MsCoppelPVM/HttpErrors.py
MsCoppelPVM/HttpResponse.py
MsCoppelPVM/HttpTransit.py
MsCoppelPVM/LogssBottle.py
MsCoppelPVM/MsManager.py
MsCoppelPVM/NatsBase.py
MsCoppelPVM/Util.py
MsCoppelPVM/Worker.py
MsCoppelPVM/http_server.py
MsCoppelPVM/loggs.py
MsCoppelPVM/loggsWrapper.py
MsCoppelPVM/microservices.py
MsCoppelPVM/ms_base.py
MsCoppelPVM/options.py
MsCoppelPVM/types.py
MsCoppelPVM/version_framework.py
MsCoppelPVMTest-0.1.dist-info/METADATA
MsCoppelPVMTest-0.1.dist-info/WHEEL
MsCoppelPVMTest-0.1.dist-info/top_level.txt
MsCoppelPVMTest-0.1.dist-info/RECORD
