Metadata-Version: 2.1
Name: MsCoppelPVMTest
Version: 0.1
Summary: Libreria para los microservicios del PVM
Home-page: https://github.com/manuelmedinae/MsCoppelPVM
Author: Jesus Lizarraga
Author-email: jesus.lizarragav@coppel.com
License: MIT
Platform: UNKNOWN
Classifier: Programming Language :: Python :: 3
Classifier: License :: OSI Approved :: MIT License
Classifier: Operating System :: OS Independent
